faceless/__init__.py
faceless/__main__.py
faceless/py.typed
faceless-0.2.0.dist-info/entry_points.txt
faceless-0.2.0.dist-info/LICENSE.rst
faceless-0.2.0.dist-info/WHEEL
faceless-0.2.0.dist-info/METADATA
faceless-0.2.0.dist-info/RECORD
