Metadata-Version: 2.1
Name: faceless
Version: 0.2.0
Summary: Faceless
Home-page: https://github.com/rcmalli/faceless
License: MIT
Author: Refik Can MALLI
Author-email: refikcan.malli@mail.polimi.it
Requires-Python: >=3.6.1,<4.0.0
Classifier: License :: OSI Approved :: MIT License
Classifier: Programming Language :: Python :: 3
Classifier: Programming Language :: Python :: 3.6
Classifier: Programming Language :: Python :: 3.7
Classifier: Programming Language :: Python :: 3.8
Requires-Dist: click (>=7.0,<8.0)
Project-URL: Changelog, https://github.com/rcmalli/faceless/releases
Project-URL: Documentation, https://faceless.readthedocs.io
Project-URL: Repository, https://github.com/rcmalli/faceless
